kadaptest/__init__.py
kadaptest/data.py
kadaptest/vin_decoder_api/__init__.py
kadaptest/vin_decoder_api/decoder.py
kadaptest3-0.0.1.dist-info/LICENSE
kadaptest3-0.0.1.dist-info/METADATA
kadaptest3-0.0.1.dist-info/WHEEL
kadaptest3-0.0.1.dist-info/top_level.txt
kadaptest3-0.0.1.dist-info/RECORD
